{
  "timestamp": "2025-09-13T13:39:32.174670",
  "processed_files": 12,
  "total_fixes": 33,
  "modified_files": 12,
  "backup_files": [
    "backups/simple_fix_329\\customers.ts.backup",
    "backups/simple_fix_329\\skus.ts.backup",
    "backups/simple_fix_329\\inventory.ts.backup",
    "backups/simple_fix_329\\users.ts.backup",
    "backups/simple_fix_329\\products.ts.backup",
    "backups/simple_fix_329\\purchases.ts.backup",
    "backups/simple_fix_329\\suppliers.ts.backup",
    "backups/simple_fix_329\\auth.ts.backup",
    "backups/simple_fix_329\\operationLogger.ts.backup",
    "backups/simple_fix_329\\ai.ts.backup",
    "backups/simple_fix_329\\assistant.ts.backup",
    "backups/simple_fix_329\\ai.ts.backup"
  ],
  "detailed_fixes": [
    "恢复customers.ts中的req参数",
    "恢复skus.ts中的req参数",
    "修复skus.ts中可选类型问题",
    "修复skus.ts中.js导入",
    "修复inventory.ts中productName:为product_name:",
    "修复users.ts中userId:为user_id:",
    "修复users.ts中createdAt:为created_at:",
    "修复products.ts中productName:为product_name:",
    "修复purchases.ts中productName:为product_name:",
    "修复purchases.ts中totalBeads:为total_beads:",
    "修复purchases.ts中BRACELET枚举",
    "修复purchases.ts中specification变量",
    "修复suppliers.ts中可选类型问题",
    "修复auth.ts中userId:为user_id:",
    "修复operationLogger.ts中purchaseId:为purchase_id:",
    "修复operationLogger.ts中userId:为user_id:",
    "修复operationLogger.ts中supplierId:为supplier_id:",
    "修复operationLogger.ts中resourceId:为resource_id:",
    "修复operationLogger.ts中createdAt:为created_at:",
    "修复operationLogger.ts中productName:为product_name:",
    "修复operationLogger.ts中productType:为product_type:",
    "修复operationLogger.ts中totalPrice:为total_price:",
    "修复operationLogger.ts中changedFields:为changed_fields:",
    "修复operationLogger.ts中data.userId为data.user_id",
    "修复operationLogger.ts中data.resourceId为data.resource_id",
    "为ai.ts添加返回语句",
    "修复assistant.ts中userId:为user_id:",
    "为assistant.ts添加返回语句",
    "修复ai.ts中beadDiameter:为bead_diameter:",
    "修复ai.ts中pieceCount:为piece_count:",
    "修复ai.ts中totalPrice:为total_price:",
    "修复ai.ts中unitPrice:为unit_price:",
    "修复ai.ts中pricePerGram:为price_per_gram:"
  ]
}