{
  "timestamp": "2025-09-13T12:38:07.008200",
  "total_changes": 4,
  "files_processed": 11,
  "backup_location": "D:\\shuijing ERP\\backend\\backups\\final_fix_20250913_123806",
  "changes_log": [
    "materials.ts: 修复特定问题 3 处",
    "products.ts: 修复通用问题 0 处",
    "purchases.ts: 修复通用问题 0 处",
    "financial.ts: 修复通用问题 0 处",
    "inventory.ts: 修复通用问题 0 处",
    "customers.ts: 修复通用问题 0 处",
    "skus.ts: 修复通用问题 0 处",
    "suppliers.ts: 修复通用问题 0 处",
    "auth.ts: 修复通用问题 0 处",
    "dashboard.ts: 修复通用问题 1 处"
  ]
}